<SpecialNames><List>
<SpecialItem Name="Item_HomeFood">
<Item_TurtleEgg>
<li Name="Rùa trứng pudding" Desc="【 Cảm tạ khảo thí người chơi: Nhân cảnh lư cung cấp thực đơn.】"/>
<li Name="Rùa bánh ga-tô" Desc="【 Cảm tạ khảo thí người chơi: Nhân cảnh lư cung cấp thực đơn.】"/>
<li Name="Chua cay rùa súp trứng" Desc="【 Cảm tạ khảo thí người chơi: Nhân cảnh lư cung cấp thực đơn.】"/>
<li Name="Rau hẹ sắc rùa trứng" Desc="【 Cảm tạ khảo thí người chơi: Nhân cảnh lư cung cấp thực đơn.】"/>
<li Name="Sinh rùa trứng trộn lẫn cơm" Desc="【 Cảm tạ khảo thí người chơi: Nhân cảnh lư cung cấp thực đơn.】"/>
<li Name="Rùa cơm trứng chiên" Desc="【 Cảm tạ khảo thí người chơi: Nhân cảnh lư cung cấp thực đơn.】"/>
<li Name="Nước nấu rùa trứng" Desc="【 Cảm tạ khảo thí người chơi: Nhân cảnh lư cung cấp thực đơn.】"/>
<li Name="Lông rùa trứng" Desc="【 Cảm tạ khảo thí người chơi: Nhân cảnh lư cung cấp thực đơn.】"/>
</Item_TurtleEgg>
<Item_SnakeEgg>
<li Name="Trứng rắn pudding" Desc="【 Cảm tạ khảo thí người chơi: Nhân cảnh lư cung cấp thực đơn.】"/>
<li Name="Trứng rắn canh" Desc="【 Cảm tạ khảo thí người chơi: Nhân cảnh lư cung cấp thực đơn.】"/>
<li Name="Chua cay trứng rắn canh" Desc="【 Cảm tạ khảo thí người chơi: Nhân cảnh lư cung cấp thực đơn.】"/>
<li Name="Rau hẹ sắc trứng rắn" Desc="【 Cảm tạ khảo thí người chơi: Nhân cảnh lư cung cấp thực đơn.】"/>
<li Name="Sinh trứng rắn trộn lẫn cơm" Desc="【 Cảm tạ khảo thí người chơi: Nhân cảnh lư cung cấp thực đơn.】"/>
<li Name="Trứng rắn cơm chiên" Desc="【 Cảm tạ khảo thí người chơi: Nhân cảnh lư cung cấp thực đơn.】"/>
<li Name="Nước nấu trứng rắn" Desc="【 Cảm tạ khảo thí người chơi: Nhân cảnh lư cung cấp thực đơn.】"/>
<li Name="Lông trứng rắn" Desc="【 Cảm tạ khảo thí người chơi: Nhân cảnh lư cung cấp thực đơn.】"/>
</Item_SnakeEgg>
<Item_ChickenEgg>
<li Name="Trứng gà pudding" Desc="【 Cảm tạ khảo thí người chơi: Nhân cảnh lư cung cấp thực đơn.】"/>
<li Name="Trứng gà canh" Desc="【 Cảm tạ khảo thí người chơi: Nhân cảnh lư cung cấp thực đơn.】"/>
<li Name="Chua cay canh trứng" Desc="【 Cảm tạ khảo thí người chơi: Nhân cảnh lư cung cấp thực đơn.】"/>
<li Name="Rau hẹ trứng ốp lếp" Desc="【 Cảm tạ khảo thí người chơi: Nhân cảnh lư cung cấp thực đơn.】"/>
<li Name="Sinh trứng gà trộn lẫn cơm" Desc="【 Cảm tạ khảo thí người chơi: Nhân cảnh lư cung cấp thực đơn.】"/>
<li Name="Trứng gà cơm chiên" Desc="【 Cảm tạ khảo thí người chơi: Nhân cảnh lư cung cấp thực đơn.】"/>
<li Name="Nước trứng gà luộc" Desc="【 Cảm tạ khảo thí người chơi: Nhân cảnh lư cung cấp thực đơn.】"/>
<li Name="Lông trứng gà" Desc="【 Cảm tạ khảo thí người chơi: Nhân cảnh lư cung cấp thực đơn.】"/>
</Item_ChickenEgg>
<Item_BoarMeat>
<li Name="Xương heo món canh" Desc=""/>
<li Name="Thịt heo bánh" Desc=""/>
<li Name="Thịt heo rừng cơm chiên" Desc=""/>
<li Name="Thịt heo quyển" Desc=""/>
<li Name="Thịt heo hầm củ cải" Desc=""/>
<li Name="Bún thịt hầm" Desc=""/>
<li Name="Nhọn tiêu thịt băm" Desc=""/>
<li Name="Nổ thịt heo sắp xếp" Desc=""/>
<li Name="Than nướng đùi heo rừng" Desc=""/>
</Item_BoarMeat>
<Item_ChickenMeat>
<li Name="Hầm thịt gà" Desc=""/>
<li Name="Thịt gà bánh" Desc=""/>
<li Name="Thịt gà cơm chiên" Desc=""/>
<li Name="Cánh gà nướng" Desc=""/>
<li Name="Chân gà cơm" Desc=""/>
<li Name="Gà tia mặt" Desc=""/>
</Item_ChickenMeat>
<Item_Beef>
<li Name="Thịt bò cơm" Desc=""/>
<li Name="Thịt bò kho" Desc=""/>
<li Name="Thịt bò canh" Desc=""/>
<li Name="Khoai tây hầm thịt bò" Desc=""/>
<li Name="Rau xào thịt bò" Desc=""/>
<li Name="Than bò nướng chân" Desc=""/>
<li Name="Cay xào thịt bò" Desc=""/>
<li Name="Thịt bò cơm chiên" Desc=""/>
<li Name="Xương trâu nồng canh" Desc=""/>
</Item_Beef>
<Item_RabbitMeat>
<li Name="Nướng thịt thỏ" Desc=""/>
<li Name="Thịt thỏ quyển" Desc=""/>
<li Name="Thịt thỏ đinh cơm chiên" Desc=""/>
<li Name="Nước chát thịt thỏ" Desc=""/>
<li Name="Thịt thỏ hầm củ cải" Desc=""/>
<li Name="Muộn thịt thỏ" Desc=""/>
<li Name="Tê cay thịt thỏ" Desc=""/>
<li Name="Chất mật thỏ" Desc=""/>
<li Name="Than nướng thịt thỏ" Desc=""/>
</Item_RabbitMeat>
<Item_WolfMeat>
<li Name="Nướng thịt sói" Desc=""/>
<li Name="Muối thô thịt sói" Desc=""/>
<li Name="Nướng sói sườn sắp xếp" Desc=""/>
<li Name="Tay bắt thịt sói" Desc=""/>
<li Name="Đỏ muộn thịt sói" Desc=""/>
<li Name="Thịt kho tàu thịt sói" Desc=""/>
<li Name="Than nướng đùi sói thịt" Desc=""/>
</Item_WolfMeat>
<Item_FishMeat>
<li Name="Thịt cá quái cơm" Desc=""/>
<li Name="Thịt cá bánh" Desc=""/>
<li Name="Thịt cá quyển" Desc=""/>
<li Name="Cá nướng" Desc=""/>
<li Name="Làm nổ cá" Desc=""/>
<li Name="Thanh thủy cá" Desc=""/>
<li Name="Cá hấp" Desc=""/>
<li Name="Cá kho" Desc=""/>
</Item_FishMeat>
<Item_SnakeMeat>
<li Name="Thịt rắn canh" Desc=""/>
<li Name="Làm nổ rắn đoạn" Desc=""/>
<li Name="Khẩu vị rắn" Desc=""/>
<li Name="Thịt kho tàu thịt rắn" Desc=""/>
<li Name="Làm kích thịt rắn" Desc=""/>
<li Name="Hương cay thịt rắn" Desc=""/>
<li Name="Rau trộn da rắn" Desc=""/>
</Item_SnakeMeat>
<Item_Wheat>
<li Name="Màn thầu" Desc=""/>
<li Name="Bánh bột mì" Desc=""/>
<li Name="Mì cay thành đô" Desc=""/>
<li Name="Mì sợi" Desc=""/>
<li Name="Mì sốt" Desc=""/>
<li Name="Bánh rán" Desc=""/>
<li Name="Dầu vừng mặt" Desc=""/>
<li Name="Mì chay" Desc=""/>
<li Name="Gà tia mặt" Desc=""/>
</Item_Wheat>
<Item_Flour>
<li Name="Màn thầu" Desc=""/>
<li Name="Bánh bột mì" Desc=""/>
<li Name="Mì cay thành đô" Desc=""/>
<li Name="Mì sợi" Desc=""/>
<li Name="Mì sốt" Desc=""/>
<li Name="Bánh rán" Desc=""/>
<li Name="Dầu vừng mặt" Desc=""/>
<li Name="Mì chay" Desc=""/>
<li Name="Gà tia mặt" Desc=""/>
</Item_Flour>
<Item_Mushroom>
<li Name="Súp nấm" Desc=""/>
<li Name="Rau xanh xào cây nấm" Desc=""/>
<li Name="Làm nổ cây nấm" Desc=""/>
<li Name="Cây nấm cơm chiên" Desc=""/>
<li Name="Cây nấm xào thịt đinh" Desc=""/>
</Item_Mushroom>
<Item_Lotusroot>
<li Name="Rau xanh xào củ sen" Desc=""/>
<li Name="Giòn xào ngó sen đinh" Desc=""/>
<li Name="Kho ngó sen phiến" Desc=""/>
<li Name="Củ sen xương heo canh" Desc=""/>
<li Name="Củ sen hầm xương sườn" Desc=""/>
<li Name="Bột củ sen" Desc=""/>
</Item_Lotusroot>
<Item_Pear>
<li Name="Tuyết lê hầm canh gà" Desc=""/>
<li Name="Lê chung cơm" Desc=""/>
<li Name="Thu lê canh" Desc=""/>
<li Name="Quả mận bắc táo đỏ nấu tuyết lê" Desc=""/>
<li Name="Hoa quỳnh nước lê canh" Desc=""/>
</Item_Pear>
<Item_Fruit>
<li Name="Cát cức hầm đậu hũ" Desc=""/>
<li Name="Cát cức củ khoai canh" Desc=""/>
<li Name="Cát cức cơm" Desc=""/>
<li Name="Cát cức nước" Desc=""/>
<li Name="Chua nước trái cây" Desc=""/>
<li Name="Chua quả cơm chiên" Desc=""/>
<li Name="Chua quả canh cá" Desc=""/>
</Item_Fruit>
<Item_FrogMeat>
<li Name="Làm nồi con ếch" Desc=""/>
<li Name="Hương xốp giòn con ếch chân" Desc=""/>
</Item_FrogMeat>
<Item_TurtleMeat>
<li Name="Đỏ muộn thịt rùa" Desc=""/>
<li Name="Giáp ngư thang" Desc=""/>
</Item_TurtleMeat>
<Item_BearMeat>
<li Name="Thịt kho tàu thịt gấu" Desc=""/>
<li Name="Đại đao tương ớt thịt gấu phiến" Desc=""/>
</Item_BearMeat>
</SpecialItem>
<SpecialItem Name="Item_DeliciousFood">
<Item_TurtleEgg>
<li Name="Ngũ vị hương kho rùa trứng" Desc="【 Cảm tạ khảo thí người chơi: Nhân cảnh lư cung cấp thực đơn.】"/>
<li Name="Bí chế mặn rùa trứng" Desc="【 Cảm tạ khảo thí người chơi: Nhân cảnh lư cung cấp thực đơn.】"/>
<li Name="Cây ăn quả nướng rùa trứng" Desc="【 Cảm tạ khảo thí người chơi: Nhân cảnh lư cung cấp thực đơn.】"/>
<li Name="Hương sắc rùa trứng" Desc="【 Cảm tạ khảo thí người chơi: Nhân cảnh lư cung cấp thực đơn.】"/>
<li Name="Thiêu đốt rùa trứng" Desc="【 Cảm tạ khảo thí người chơi: Nhân cảnh lư cung cấp thực đơn.】"/>
<li Name="Da hổ rùa trứng" Desc="【 Cảm tạ khảo thí người chơi: Nhân cảnh lư cung cấp thực đơn.】"/>
</Item_TurtleEgg>
<Item_SnakeEgg>
<li Name="Ngũ vị hương kho trứng rắn" Desc="【 Cảm tạ khảo thí người chơi: Nhân cảnh lư cung cấp thực đơn.】"/>
<li Name="Bí chế mặn trứng rắn" Desc="【 Cảm tạ khảo thí người chơi: Nhân cảnh lư cung cấp thực đơn.】"/>
<li Name="Cây ăn quả rắn nướng trứng" Desc="【 Cảm tạ khảo thí người chơi: Nhân cảnh lư cung cấp thực đơn.】"/>
<li Name="Hương sắc trứng rắn" Desc="【 Cảm tạ khảo thí người chơi: Nhân cảnh lư cung cấp thực đơn.】"/>
<li Name="Thiêu đốt trứng rắn" Desc="【 Cảm tạ khảo thí người chơi: Nhân cảnh lư cung cấp thực đơn.】"/>
<li Name="Da hổ trứng rắn" Desc="【 Cảm tạ khảo thí người chơi: Nhân cảnh lư cung cấp thực đơn.】"/>
</Item_SnakeEgg>
<Item_ChickenEgg>
<li Name="Ngũ vị hương nấu trứng gà" Desc="【 Cảm tạ khảo thí người chơi: Nhân cảnh lư cung cấp thực đơn.】"/>
<li Name="Bí chế mặn trứng gà" Desc="【 Cảm tạ khảo thí người chơi: Nhân cảnh lư cung cấp thực đơn.】"/>
<li Name="Cây ăn quả gà nướng trứng" Desc="【 Cảm tạ khảo thí người chơi: Nhân cảnh lư cung cấp thực đơn.】"/>
<li Name="Hương trứng ốp lếp" Desc="【 Cảm tạ khảo thí người chơi: Nhân cảnh lư cung cấp thực đơn.】"/>
<li Name="Thiêu đốt trứng gà" Desc="【 Cảm tạ khảo thí người chơi: Nhân cảnh lư cung cấp thực đơn.】"/>
<li Name="Da hổ trứng gà" Desc="【 Cảm tạ khảo thí người chơi: Nhân cảnh lư cung cấp thực đơn.】"/>
</Item_ChickenEgg>
<Item_BoarMeat>
<li Name="Kho lỗ tai heo" Desc=""/>
<li Name="Thịt heo viên thuốc" Desc=""/>
<li Name="Thịt kho tàu móng heo" Desc=""/>
<li Name="Ớt đỏ xào lăn thịt heo rừng" Desc=""/>
<li Name="Thịt heo sủi cảo" Desc=""/>
<li Name="Chất mật thịt heo mứt" Desc=""/>
<li Name="Hành hương heo nướng miếng thịt" Desc=""/>
<li Name="Tương hương xương sườn tia" Desc=""/>
<li Name="Chất mật thịt heo mứt" Desc=""/>
</Item_BoarMeat>
<Item_ChickenMeat>
<li Name="Cung bảo kê đinh" Desc=""/>
<li Name="Lớn gà rán" Desc=""/>
<li Name="Đùi gà chiên" Desc=""/>
</Item_ChickenMeat>
<Item_Beef>
<li Name="Nước nấu thịt bò" Desc=""/>
<li Name="Bên trên canh mập trâu" Desc=""/>
<li Name="Đun nhừ móng trâu gân" Desc=""/>
<li Name="Thịt bò hoàn" Desc=""/>
<li Name="Thịt bò sủi cảo" Desc=""/>
<li Name="Xào lăn thịt bò tia" Desc=""/>
<li Name="Nồi đất thịt bò" Desc=""/>
<li Name="Thịt bò loạn hầm" Desc=""/>
<li Name="Hoàng Kim Ngưu thịt" Desc=""/>
</Item_Beef>
<Item_RabbitMeat>
<li Name="Hương cay thỏ đầu" Desc=""/>
<li Name="Nướng toàn thỏ" Desc=""/>
<li Name="Hương cay xào lăn thỏ đinh" Desc=""/>
<li Name="Da giòn thỏ" Desc=""/>
<li Name="Muối tiêu thỏ" Desc=""/>
<li Name="Khương hành muộn thịt thỏ" Desc=""/>
<li Name="Bích thỏ rừng" Desc=""/>
<li Name="Nhảy cầu thỏ" Desc=""/>
<li Name="Chấm nước thịt thỏ" Desc=""/>
</Item_RabbitMeat>
<Item_WolfMeat>
<li Name="Hầm thịt sói" Desc=""/>
<li Name="Núi tiêu thịt sói" Desc=""/>
<li Name="Cây thì là thịt sói" Desc=""/>
<li Name="Khương bạo thịt sói" Desc=""/>
</Item_WolfMeat>
<Item_FishMeat>
<li Name="Cá luộc" Desc=""/>
<li Name="Thịt cá viên thuốc" Desc=""/>
<li Name="Cá bánh ngọt" Desc=""/>
<li Name="Ba cá nồi" Desc=""/>
<li Name="Chua canh cá" Desc=""/>
<li Name="Rượu nhưỡng cá" Desc=""/>
<li Name="Hương sắc lát cá" Desc=""/>
<li Name="Canh loãng muộn cá" Desc=""/>
<li Name="Chặt tiêu đầu cá" Desc=""/>
</Item_FishMeat>
<Item_SnakeMeat>
<li Name="Nước bọt rắn" Desc=""/>
<li Name="Rắn nước cháo" Desc=""/>
<li Name="Hầm thịt rắn" Desc=""/>
<li Name="Hoàng muộn rắn" Desc=""/>
<li Name="Hành bạo rắn đoạn" Desc=""/>
<li Name="Kim châm rắn tia" Desc=""/>
<li Name="Kim Long canh" Desc=""/>
<li Name="Ngũ thải xào rắn tia" Desc=""/>
<li Name="Ba khuẩn thịt rắn" Desc=""/>
</Item_SnakeMeat>
<Item_Wheat>
<li Name="Bún tàu" Desc=""/>
<li Name="Chùy mặt" Desc=""/>
<li Name="Quẳng mặt" Desc=""/>
<li Name="Muộn mặt" Desc=""/>
<li Name="Che phủ mặt" Desc=""/>
<li Name="Nắm chặt phiến" Desc=""/>
<li Name="Bánh đậu bao" Desc=""/>
<li Name="Sữa hoàng bao" Desc=""/>
<li Name="Bịt đường" Desc=""/>
<li Name="Bánh nướng" Desc=""/>
</Item_Wheat>
<Item_Flour>
<li Name="Bún tàu" Desc=""/>
<li Name="Chùy mặt" Desc=""/>
<li Name="Quẳng mặt" Desc=""/>
<li Name="Muộn mặt" Desc=""/>
<li Name="Che phủ mặt" Desc=""/>
<li Name="Nắm chặt phiến" Desc=""/>
<li Name="Bánh đậu bao" Desc=""/>
<li Name="Sữa hoàng bao" Desc=""/>
<li Name="Bịt đường" Desc=""/>
<li Name="Bánh nướng" Desc=""/>
</Item_Flour>
<Item_Mushroom>
<li Name="Tươi ma Bát Bảo quái" Desc=""/>
<li Name="Cây nấm canh loãng tưới cơm" Desc=""/>
<li Name="Nướng cây nấm" Desc=""/>
<li Name="Cây nấm hầm khoai tây" Desc=""/>
<li Name="Cây nấm quyển" Desc=""/>
<li Name="Ngũ thải cây nấm liều" Desc=""/>
<li Name="Tỏi nướng kim châm nấm" Desc=""/>
</Item_Mushroom>
<Item_Lotusroot>
<li Name="Ngó sen hộp" Desc=""/>
<li Name="Chua Maylene ngó sen canh" Desc=""/>
<li Name="Dấm đường ngó sen phiến" Desc=""/>
<li Name="Ngó sen tâm chưng cơm" Desc=""/>
<li Name="Ngũ vị hương củ sen" Desc=""/>
</Item_Lotusroot>
<Item_Pear>
<li Name="Bách hợp băng lê phiến" Desc=""/>
<li Name="Mật lê song xông uống" Desc=""/>
<li Name="Nấm tuyết nhưỡng nhỏ lê" Desc=""/>
<li Name="Thu mứt lê" Desc=""/>
</Item_Pear>
<Item_Fruit>
<li Name="Cát cức bánh ngọt" Desc=""/>
<li Name="Cát cức đậu xanh tương" Desc=""/>
<li Name="Thủy tinh cát cức" Desc=""/>
<li Name="Chua mứt hoa quả thịt nướng" Desc=""/>
<li Name="Chua quả nướng bánh" Desc=""/>
<li Name="Chua quả muộn cá" Desc=""/>
</Item_Fruit>
<Item_FrogMeat>
<li Name="Làm nồi con ếch" Desc=""/>
<li Name="Hương xốp giòn con ếch chân" Desc=""/>
</Item_FrogMeat>
<Item_TurtleMeat>
<li Name="Đỏ muộn thịt rùa" Desc=""/>
<li Name="Giáp ngư thang" Desc=""/>
</Item_TurtleMeat>
<Item_BearMeat>
<li Name="Chưng tay gấu" Desc=""/>
<li Name="Thịt kho tàu tay gấu" Desc=""/>
</Item_BearMeat>
</SpecialItem>
<SpecialItem Name="Item_DelicacyFood">
<Item_TurtleEgg>
<li Name="Ngũ sắc quái trứng" Desc="Đem nguyên liệu nấu ăn nhiều lần thêm nước nước nấu sau thành hình cắt miếng, rải lên ngũ sắc linh quả mài bột phấn, lấy thủ pháp đặc biệt lật xào. Hương vị ngọt, vừa miệng không ngán.【 Cảm tạ khảo thí người chơi: Nhân cảnh lư cung cấp thực đơn.】"/>
<li Name="Long tức trứng" Desc=" Lấy nhiệt độ cực cao Ngô Đồng Mộc tro muộn chế nguyên liệu nấu ăn bảy canh giờ, không thêm ngoại vật, để trứng bản thân cảm giác phát huy đến cực hạn, đồng thời có chút cây ăn quả mùi thơm ngát cùng Hỏa linh lực bạo tạc cảm giác khiến người dư vị vô tận.【 Cảm tạ khảo thí người chơi: Nhân cảnh lư cung cấp thực đơn.】"/>
</Item_TurtleEgg>
<Item_SnakeEgg>
<li Name="Ngũ sắc quái trứng" Desc="Đem nguyên liệu nấu ăn nhiều lần thêm nước nước nấu sau thành hình cắt miếng, rải lên ngũ sắc linh quả mài bột phấn, lấy thủ pháp đặc biệt lật xào. Hương vị ngọt, vừa miệng không ngán.【 Cảm tạ khảo thí người chơi: Nhân cảnh lư cung cấp thực đơn.】"/>
<li Name="Long tức trứng" Desc=" Lấy nhiệt độ cực cao Ngô Đồng Mộc tro muộn chế nguyên liệu nấu ăn bảy canh giờ, không thêm ngoại vật, để trứng bản thân cảm giác phát huy đến cực hạn, đồng thời có chút cây ăn quả mùi thơm ngát cùng Hỏa linh lực bạo tạc cảm giác khiến người dư vị vô tận.【 Cảm tạ khảo thí người chơi: Nhân cảnh lư cung cấp thực đơn.】"/>
</Item_SnakeEgg>
<Item_ChickenEgg>
<li Name="Ngũ sắc quái trứng" Desc="Đem nguyên liệu nấu ăn nhiều lần thêm nước nước nấu sau thành hình cắt miếng, rải lên ngũ sắc linh quả mài bột phấn, lấy thủ pháp đặc biệt lật xào. Hương vị ngọt, vừa miệng không ngán.【 Cảm tạ khảo thí người chơi: Nhân cảnh lư cung cấp thực đơn.】"/>
<li Name="Long tức trứng" Desc=" Lấy nhiệt độ cực cao Ngô Đồng Mộc tro muộn chế nguyên liệu nấu ăn bảy canh giờ, không thêm ngoại vật, để trứng bản thân cảm giác phát huy đến cực hạn, đồng thời có chút cây ăn quả mùi thơm ngát cùng Hỏa linh lực bạo tạc cảm giác khiến người dư vị vô tận.【 Cảm tạ khảo thí người chơi: Nhân cảnh lư cung cấp thực đơn.】"/>
</Item_ChickenEgg>
<Item_BoarMeat>
<li Name="Vùng bỏ hoang chi phong" Desc="Lấy lửa mạnh đối heo chân sau thịt tiến hành độ khó cao nướng, hình thành phong cách khác lạ ba tầng cảm giác: Ngoại tầng vàng và giòn nóng bỏng, trung tầng nhai kình mười phần, tầng bên trong nhiều chất lỏng tươi non, nếm qua về sau phảng phất đặt mình vào vùng bỏ hoang, là rất có thảo nguyên phong cách món ăn."/>
<li Name="Nhị Thập Tứ Kiều Minh Nguyệt Dạ" Desc="Đem lợn rừng thịt sườn thuận thành tia, ướp gia vị ngon miệng, lại đoàn nhập đậu hũ chẻ thành cầu bên trong, làm hai mươi bốn hạt, để vào canh loãng lửa nhỏ chậm hầm thu nước mà thành xa hoa món ăn."/>
</Item_BoarMeat>
<Item_Beef>
<li Name="Lục Liễu phù phong" Desc="Đem thịt bò cắt thành tơ mỏng, lấy cao tiêu chuẩn lật xào sau bàn ghép, cảm giác thanh đạm, nhưng dư vị vô tận. Bởi vì thịt băm tinh tế, cho nên phi thường ngon miệng, nhưng là không cẩn thận liền sẽ mất đi hỏa hầu, làm chất thịt già đi."/>
<li Name="Ba tia trâu lưỡi" Desc="Trâu lưỡi hương vị ngọt ngon, chất thịt cực non, ba tia trâu lưỡi càng đem cái này một đặc chất phát huy đến cực hạn, lấy rất ít hương liệu đem trâu lưỡi lúc đầu cảm giác cùng hương vị phát huy đến cực hạn."/>
</Item_Beef>
<Item_RabbitMeat>
<li Name="Thủy tinh thỏ" Desc="Lấy thủ pháp đặc biệt xào nấu thịt thỏ, làm cho nửa thấu thoáng như thủy tinh. Cảm giác đạn răng tươi hương, là sắc hương vị đều đủ mỹ thực."/>
<li Name="Năm tiên thỏ" Desc="Lấy năm loại hương liệu cùng thỏ đinh xào chế, năm loại hương vị trùng điệp phụ trợ, làm thịt thỏ cấp độ tươi sáng. Chỗ khó ở chỗ hỏa hầu đem khống, một khi mất cân bằng sẽ làm hương liệu hỗn hợp, phá hư cảm giác cấp độ."/>
</Item_RabbitMeat>
<Item_WolfMeat>
<li Name="Thiên cẩu thôn nhật" Desc="Lấy lớn tương cùng mấy chục loại nguyên liệu nấu ăn xào nấu thành thịt sói nấu canh, mới nhìn không gặp ảo diệu, theo nước canh một chút xíu uống hết, trong đó nguyên liệu nấu ăn theo thứ tự lộ ra, đều có phong vị."/>
<li Name="Liệt hỏa đốt tâm" Desc="Sói lưng ưu chất nhất thịt lấy quả ớt lặp đi lặp lại nấu nướng, dù là trời đông giá rét thời điểm, cửa vào cũng cảm thấy toàn thân khô nóng sinh ấm, cảm giác tươi cay, muốn ngừng mà không được."/>
</Item_WolfMeat>
<Item_FishMeat>
<li Name="Hóa rồng canh" Desc="Lấy ngư dược hóa rồng chi ý, này canh bí quyết tại phức tạp nấu nướng trình tự cùng hương liệu sử dụng bên trên, hương vị tươi hương viễn siêu phổ thông thịt cá xử lý."/>
<li Name="Dê phương giấu cá" Desc="Đem cá đặt cắt khối lớn thịt dê bên trong, tăng thêm gia vị cùng nấu, vị ngon vô cùng. Bởi vì thức ăn thuỷ sản dê tươi hợp thành một thể, vị càng tươi. Thịt dê xốp giòn nát vị hương, bên trong giấu thịt cá tươi non."/>
</Item_FishMeat>
<Item_SnakeMeat>
<li Name="Long phượng trình tường" Desc="Đem thịt rắn cùng thịt gà trước tiến hành ướp gia vị, sau đó hợp nhập nồi đun nước lửa nhỏ đun nhừ, thẳng đến nước canh thu làm, hai loại thịt tươi hương lẫn nhau phụ trợ, hương vị tuyệt hảo."/>
<li Name="Quy Xà bàn" Desc="Đem thịt rùa thịt rắn cùng một chỗ nấu nướng nấu chín, thịt rùa cùng thịt rắn cảm giác kình đạo ngon miệng, là một đạo đại bổ món ngon."/>
</Item_SnakeMeat>
<Item_Flour>
<li Name="Ba ngàn phiền não" Desc="Nhỏ như sợi tóc bánh bột, hợp với bốn loại đặc chế kho canh, cực kỳ ngon miệng mà lại vào miệng tan đi, là bánh bột cực nghệ."/>
<li Name="Rót canh ngũ đức bao lớn" Desc="Truyền lại từ cung đình nấu nướng, đem bao lớn bên trong phân năm các, lấp nhập năm loại đặc chất hãm liêu, biểu tượng nhân nghĩa lễ trí tín ngũ đức. Như lấy lửa nhỏ chưng, thì ngũ vị đều đủ; Như lấy đại hỏa chưng, trong bọc mỏng da bởi vì áp lực mà vỡ tan, tương liệu ngẫu nhiên hỗn hợp, lại sinh sôi gian lận biến vạn hóa khẩu vị."/>
<li Name="Bánh bao nắm" Desc="Đến từ một tòa phương nam bờ biển thành thị đặc chế bánh bột, xoã tung ngọt mềm, cửa vào hương nhu, cảm giác mười phần mỹ diệu. Nó ký thác tòa thành thị kia hồi ức."/>
</Item_Flour>
<Item_Wheat>
<li Name="Ba ngàn phiền não" Desc="Nhỏ như sợi tóc bánh bột, hợp với bốn loại đặc chế kho canh, cực kỳ ngon miệng mà lại vào miệng tan đi, là bánh bột cực nghệ."/>
<li Name="Rót canh ngũ đức bao lớn" Desc="Truyền lại từ cung đình nấu nướng, đem bao lớn bên trong phân năm các, lấp nhập năm loại đặc chất hãm liêu, biểu tượng nhân nghĩa lễ trí tín ngũ đức. Như lấy lửa nhỏ chưng, thì ngũ vị đều đủ; Như lấy đại hỏa chưng, trong bọc mỏng da bởi vì áp lực mà vỡ tan, tương liệu ngẫu nhiên hỗn hợp, lại sinh sôi gian lận biến vạn hóa khẩu vị."/>
</Item_Wheat>
<Item_Mushroom>
<li Name="Trời đường phố mưa nhỏ nhuận như bơ" Desc="Đem hình dạng hoàn hảo hợp quy tắc cây nấm đứng ở bạch đậu hũ bên trên, cũng tại chưng chế quá trình bên trong tiếp tục xối nhập đặc chế nước canh. Ra nồi lúc đầu nấm bên trên còn mang dịch giọt, cho nên gọi tên."/>
</Item_Mushroom>
<Item_Lotusroot>
<li Name="Thất xảo chưng Hồng ngó sen" Desc="Vốn là tế thiên sở dụng món ăn, sau chảy vào dân gian trở thành món ăn nổi tiếng. Lấy thất khiếu lớn củ sen làm vật liệu chính, phân biệt lấp nhập tam sinh bốn súc đặc chế thịt băm, chưng chín sau cắt miếng thịnh bàn. Mặc dù trình tự đơn giản, nhưng là đối nguyên liệu nấu ăn cùng trù nghệ yêu cầu cực cao."/>
<li Name="Vượt Long Môn" Desc="Đem trọn chỉ lớn ngó sen hai đầu cắt đứt, ở giữa lỗ thủng đả thông. Mà từ đứng sau tại đặc chế uyên ương trong nồi lớn, một mặt canh loãng thêm đá, một mặt nước dùng để cạnh nhau nhập Vân Mộng Trạch đặc sản tiểu ngân cá cũng lấy lửa mạnh làm nóng, sau đó lên bàn."/>
</Item_Lotusroot>
<Item_Pear>
<li Name="Thủy tinh lê điêu" Desc="Đem chất lượng tốt quả lê cấp đống, sau đó đi da, quả lê thịt quả lại biến thành hơi mờ chất liệu. Trong thời gian cực ngắn đem điêu khắc thành đủ loại hình dạng hiện lên bàn, sương trắng bốc hơi bên trong hơi mờ tinh xảo pho tượng như ẩn như hiện, cửa vào băng thoải mái thơm ngọt. Là một đạo sắc hương vị đều đủ mỹ thực."/>
<li Name="Băng khánh cánh ve" Desc="Đem lên chờ tuyết lê đi da, cắt nữa thành cánh ve phiến mỏng, tầng tầng dán ở khương nước chè chế thành băng khánh vách trong. Dùng ăn quá trình bên trong, mỏng như cánh ve lê phiến ngọt giòn ngon miệng, ăn xong lê phiến càng có thể uống băng khánh hòa tan sau nước canh. Tuy là đồ uống lạnh, nhưng là không phân mùa mỹ vị."/>
</Item_Pear>
<Item_Fruit>
<li Name="Trăm quả hợp thành" Desc="Lấy bình thường nhất hoang dại chua quả mọng vì nguyên liệu, lấy thủ pháp cao siêu cùng dùng tài liệu đem điều chế thành các loại hoa quả hương vị, sau đó hợp ở một chậu, không có tan mục nát thành thần kỳ cao siêu trù nghệ không cách nào hoàn thành món ăn này phẩm."/>
</Item_Fruit>
<Item_FrogMeat>
<li Name="Làm nồi con ếch" Desc=""/>
<li Name="Hương xốp giòn con ếch chân" Desc=""/>
</Item_FrogMeat>
<Item_TurtleMeat>
<li Name="Quy Xà bàn" Desc="Đem thịt rùa thịt rắn cùng một chỗ nấu nướng nấu chín, thịt rùa cùng thịt rắn cảm giác kình đạo ngon miệng, là một đạo đại bổ món ngon."/>
</Item_TurtleMeat>
<Item_BearMeat>
<li Name="Thủy tinh tay gấu" Desc=""/>
</Item_BearMeat>
<Item_ChickenMeat>
<li Name="Kim gáy báo sáng" Desc=""/>
</Item_ChickenMeat>
</SpecialItem>
</List></SpecialNames>
